Metadata-Version: 2.1
Name: frases
Version: 0.1.3
Summary: API de frases
Home-page: https://frases.atico.ga/api
Author: Luqaska
Project-URL: Changelog, https://github.com/Luqaska/frases.py/releases
Project-URL: Bug Tracker, https://github.com/Luqaska/frases.py/issues
Project-URL: Source Code, https://github.com/Luqaska/frases.py
Keywords: API,frases
Requires: requests
License-File: LICENSE.txt
